smorfinder/__init__.py
smorfinder/finalize.py
smorfinder/help.py
smorfinder/hmmsearch.py
smorfinder/main.py
smorfinder/model.py
smorfinder/prodigal.py
smorfinder/run.py
smorfinder/bin/linux/hmmscan
smorfinder/bin/linux/hmmsearch
smorfinder/bin/linux/prodigal
smorfinder/bin/mac/hmmscan
smorfinder/bin/mac/hmmsearch
smorfinder/bin/mac/prodigal
smorfinder-1.0.0.dist-info/LICENSE.txt
smorfinder-1.0.0.dist-info/METADATA
smorfinder-1.0.0.dist-info/WHEEL
smorfinder-1.0.0.dist-info/entry_points.txt
smorfinder-1.0.0.dist-info/top_level.txt
smorfinder-1.0.0.dist-info/RECORD
